LICENSE
MANIFEST.in
README.rst
requirements.txt
setup.py
./sesame/__init__.py
./sesame/cli.py
./sesame/core.py
./sesame/utils.py
scripts/sesame
sesame.egg-info/PKG-INFO
sesame.egg-info/SOURCES.txt
sesame.egg-info/dependency_links.txt
sesame.egg-info/requires.txt
sesame.egg-info/top_level.txt