Metadata-Version: 1.0
Name: sesame
Version: 0.3.2
Summary: Encryption tool for application configs.
Home-page: http://github.com/mafrosis/sesame
Author: Matt Black
Author-email: dev@mafro.net
License: Copyright (c) 2013, Matt Black
